{"openapi":"3.0.1","info":{"title":"open-api doc","version":"v1"},"paths":{"/":{"get":{"operationId":"index","tags":["IndexController"],"responses":{"200":{"description":"200 response","content":{"application/json":{"schema":{"type":"string"}}}}},"parameters":[]}},"/v3/api-docs":{"get":{"operationId":"apiDocs","tags":["IndexController"],"responses":{"200":{"description":"200 response","content":{"application/json":{"schema":{"type":"string"}}}}},"parameters":[]}},"/healthcheck":{"get":{"operationId":"healthcheck","tags":["IndexController"],"responses":{"200":{"description":"200 response","content":{"application/json":{"schema":{"$ref":"#/components/schemas/ApiResponseOfVoid"}}}}},"parameters":[]}},"/customer":{"post":{"operationId":"createCustomer","tags":["CustomerController"],"responses":{"200":{"description":"200 response","content":{"application/json":{"schema":{"type":"object"}}}}},"requestBody":{"required":true,"content":{"application/json":{"schema":{"$ref":"#/components/schemas/CustomerRequest"}}}},"parameters":[]}},"/customer/details/{accountNumber}":{"get":{"operationId":"getDetails","tags":["CustomerController"],"responses":{"200":{"description":"200 response","content":{"application/json":{"schema":{"type":"object","nullable":true}}}}},"parameters":[{"name":"accountNumber","in":"path","required":true,"schema":{"type":"string"}}]}},"/customer/details/{customerId}":{"put":{"operationId":"update","tags":["CustomerController"],"responses":{"200":{"description":"200 response","content":{"application/json":{"schema":{"$ref":"#/components/schemas/ApiResponseOfNumber"}}}}},"requestBody":{"required":true,"content":{"application/json":{"schema":{"$ref":"#/components/schemas/CustomerRequest"}}}},"parameters":[{"name":"customerId","in":"path","required":true,"schema":{"type":"string"}}]}},"/customer/account-details/{customerId}":{"put":{"operationId":"additionalAccount","tags":["CustomerController"],"responses":{"200":{"description":"200 response","content":{"application/json":{"schema":{"$ref":"#/components/schemas/ApiResponseOfNumber"}}}}},"requestBody":{"required":true,"content":{"application/json":{"schema":{"$ref":"#/components/schemas/AdditionalAccountRequest"}}}},"parameters":[{"name":"customerId","in":"path","required":true,"schema":{"type":"string"}}]}},"/customer/all":{"get":{"operationId":"allCustomers","tags":["CustomerController"],"responses":{"200":{"description":"200 response","content":{"application/json":{"schema":{"$ref":"#/components/schemas/SearchResultOfCustomer"}}}}},"parameters":[{"in":"query","name":"limit","schema":{"type":"number","uniqueItems":false}},{"in":"query","name":"offset","schema":{"type":"number","uniqueItems":false}}]}},"/transaction/deposit":{"post":{"operationId":"deposit","tags":["TransactionController"],"responses":{"200":{"description":"200 response","content":{"application/json":{"schema":{"type":"object"}}}}},"requestBody":{"required":true,"content":{"application/json":{"schema":{"$ref":"#/components/schemas/TransactionRequest"}}}},"parameters":[]}},"/transaction/withdraw":{"post":{"operationId":"withdraw","tags":["TransactionController"],"responses":{"200":{"description":"200 response","content":{"application/json":{"schema":{"type":"object"}}}}},"requestBody":{"required":true,"content":{"application/json":{"schema":{"$ref":"#/components/schemas/TransactionRequest"}}}},"parameters":[]}},"/transaction/history/{nuban}":{"get":{"operationId":"history","tags":["TransactionController"],"responses":{"200":{"description":"200 response","content":{"application/json":{"schema":{"type":"object"}}}}},"parameters":[{"name":"nuban","in":"path","required":true,"schema":{"type":"string"}}]}},"/address/{addressId}":{"put":{"operationId":"updateAddress","tags":["AddressController"],"responses":{"200":{"description":"200 response","content":{"application/json":{"schema":{"$ref":"#/components/schemas/ApiResponseOfNumber"}}}}},"requestBody":{"required":true,"content":{"application/json":{"schema":{"$ref":"#/components/schemas/AddressRequest"}}}},"parameters":[{"name":"addressId","in":"path","required":true,"schema":{"type":"string"}}]}}},"components":{"schemas":{"ApiResponseOfVoid":{"type":"object","properties":{"success":{"type":"boolean"},"message":{"type":"string"}}},"CustomerRequest":{"type":"object","properties":{"first_name":{"type":"string"},"last_name":{"type":"string"},"city":{"type":"string"},"country":{"type":"string"},"state":{"type":"string"},"type":{"type":"string","enum":["Savings","Corporate"]}}},"ApiResponseOfNumber":{"type":"object","properties":{"success":{"type":"boolean"},"message":{"type":"string"}}},"AdditionalAccountRequest":{"type":"object","properties":{"type":{"type":"string","enum":["Savings","Corporate"]}}},"SearchResultOfCustomer":{"type":"object","properties":{"limit":{"type":"number"},"offset":{"type":"number"},"total":{"type":"number"},"results":{"type":"array","items":{"$ref":"#/components/schemas/Customer"},"uniqueItems":false}}},"Customer":{"type":"object","properties":{"id":{"type":"number"},"first_name":{"type":"string"},"last_name":{"type":"string"},"address":{"$ref":"#/components/schemas/Address"},"passport":{"$ref":"#/components/schemas/Passport"},"accountDetails":{"type":"array","items":{"$ref":"#/components/schemas/Account"},"uniqueItems":false}}},"Address":{"type":"object","properties":{"id":{"type":"number"},"city":{"type":"string"},"state":{"type":"string"},"country":{"type":"string"},"customer":{"$ref":"#/components/schemas/Customer"}}},"Passport":{"type":"object","properties":{"id":{"type":"number"},"link":{"type":"string"},"date":{"type":"string","format":"date-time"},"customer":{"$ref":"#/components/schemas/Customer"}}},"Account":{"type":"object","properties":{"id":{"type":"number"},"type":{"type":"string"},"currentBalance":{"type":"number"},"dateCreated":{"type":"string","format":"date-time"},"nuban":{"type":"number"},"limit":{"type":"number"},"customer":{"$ref":"#/components/schemas/Customer"},"transactions":{"type":"array","items":{"$ref":"#/components/schemas/Transaction"},"uniqueItems":false}}},"Transaction":{"type":"object","properties":{"id":{"type":"number"},"type":{"type":"string","enum":["Withdrawal","Deposit"]},"balance":{"type":"number"},"date":{"type":"string","format":"date-time"},"amount":{"type":"number"},"status":{"type":"string","enum":["Failed","Success","Flagged","Pending"]},"account":{"$ref":"#/components/schemas/Account"}}},"PageRequest":{"type":"object","properties":{"limit":{"type":"number"},"offset":{"type":"number"}}},"TransactionRequest":{"type":"object","properties":{"type":{"type":"string","enum":["Withdrawal","Deposit"]},"nuban":{"type":"number"},"amount":{"type":"number"}}},"AddressRequest":{"type":"object","properties":{"city":{"type":"string"},"country":{"type":"string"},"state":{"type":"string"}}}}}}